pygarble/__init__.py
pygarble/core.py
pygarble/data/__init__.py
pygarble/data/bigrams.py
pygarble/data/trigrams.py
pygarble/data/words.py
pygarble/strategies/__init__.py
pygarble/strategies/base.py
pygarble/strategies/bigram_probability.py
pygarble/strategies/character_frequency.py
pygarble/strategies/compression_ratio.py
pygarble/strategies/consonant_sequence.py
pygarble/strategies/english_word_validation.py
pygarble/strategies/entropy_based.py
pygarble/strategies/hex_string.py
pygarble/strategies/keyboard_pattern.py
pygarble/strategies/letter_frequency.py
pygarble/strategies/letter_position.py
pygarble/strategies/markov_chain.py
pygarble/strategies/mojibake.py
pygarble/strategies/ngram_frequency.py
pygarble/strategies/pattern_matching.py
pygarble/strategies/pronounceability.py
pygarble/strategies/rare_trigram.py
pygarble/strategies/repetition.py
pygarble/strategies/statistical_analysis.py
pygarble/strategies/symbol_ratio.py
pygarble/strategies/unicode_script.py
pygarble/strategies/vowel_pattern.py
pygarble/strategies/vowel_ratio.py
pygarble/strategies/word_length.py
pygarble/strategies/word_lookup.py
pygarble-0.5.0.dist-info/licenses/LICENSE
tests/__init__.py
tests/test_core.py
tests/test_detector.py
tests/test_edge_cases.py
tests/test_new_features.py
tests/test_new_strategies.py
tests/test_precision_strategies.py
tests/test_strategies.py
pygarble-0.5.0.dist-info/METADATA
pygarble-0.5.0.dist-info/WHEEL
pygarble-0.5.0.dist-info/top_level.txt
pygarble-0.5.0.dist-info/RECORD
