Metadata-Version: 2.4
Name: pygarble
Version: 0.5.0
Summary: A Python package for detecting garbled text using multiple detection strategies with a scikit-learn-like interface
Home-page: https://github.com/brightertiger/pygarble
Author: Your Name
Author-email: Ujjwal <ujjwal@example.com>
License: MIT
Project-URL: Homepage, https://github.com/brightertiger/pygarble
Project-URL: Repository, https://github.com/brightertiger/pygarble
Project-URL: Issues, https://github.com/brightertiger/pygarble/issues
Project-URL: Documentation, https://github.com/brightertiger/pygarble#readme
Keywords: garble,text,detection,nlp,machine-learning,scikit-learn
Classifier: Development Status :: 4 - Beta
Classifier: Intended Audience :: Developers
Classifier: Intended Audience :: Science/Research
Classifier: License :: OSI Approved :: MIT License
Classifier: Operating System :: OS Independent
Classifier: Programming Language :: Python :: 3
Classifier: Programming Language :: Python :: 3.8
Classifier: Programming Language :: Python :: 3.9
Classifier: Programming Language :: Python :: 3.10
Classifier: Programming Language :: Python :: 3.11
Classifier: Programming Language :: Python :: 3.12
Classifier: Topic :: Scientific/Engineering :: Artificial Intelligence
Classifier: Topic :: Text Processing :: Linguistic
Classifier: Topic :: Software Development :: Libraries :: Python Modules
Requires-Python: >=3.8
License-File: LICENSE
Provides-Extra: spellchecker
Requires-Dist: pyspellchecker>=0.7.0; extra == "spellchecker"
Provides-Extra: all
Requires-Dist: pyspellchecker>=0.7.0; extra == "all"
Provides-Extra: dev
Requires-Dist: pytest>=6.0; extra == "dev"
Requires-Dist: pytest-cov>=2.0; extra == "dev"
Requires-Dist: black>=21.0; extra == "dev"
Requires-Dist: flake8>=3.8; extra == "dev"
Requires-Dist: mypy>=0.800; extra == "dev"
Dynamic: author
Dynamic: home-page
Dynamic: license-file
Dynamic: requires-python
